test_add_mcp/__init__.py
test_add_mcp-0.1.0.dist-info/METADATA
test_add_mcp-0.1.0.dist-info/WHEEL
test_add_mcp-0.1.0.dist-info/entry_points.txt
test_add_mcp-0.1.0.dist-info/RECORD
